Sources/__init__.py
Sources/data_sync.py
localization_sync-0.2.0.dist-info/LICENSE
localization_sync-0.2.0.dist-info/METADATA
localization_sync-0.2.0.dist-info/WHEEL
localization_sync-0.2.0.dist-info/entry_points.txt
localization_sync-0.2.0.dist-info/top_level.txt
localization_sync-0.2.0.dist-info/RECORD
