Metadata-Version: 2.1
Name: localization-sync
Version: 0.2.0
Summary: A python script that generates localization files for iOS and Android projects from a public GoogleSheet.
Home-page: https://github.com/r-dent/LocalizationSync
Author: Roman Gille
Author-email: developer@romangille.com
Classifier: Programming Language :: Python :: 3
Classifier: License :: OSI Approved :: MIT License
Classifier: Operating System :: OS Independent
Classifier: Intended Audience :: Developers
Classifier: Topic :: Software Development :: Code Generators
Classifier: Topic :: Software Development :: Localization
Classifier: Topic :: Software Development :: Embedded Systems
Classifier: Topic :: Utilities
Requires-Python: >=3.6
License-File: LICENSE
Requires-Dist: pyexcel-ods
